<?xml version="1.0" encoding="UTF-8"?>
<Defs>

  <RecipeDef Name="HeavyEnigmaticMechanoidRecipe" ParentName="BaseEnigmaticMechanoidRecipe" Abstract="True">
    <gestationCycles>4</gestationCycles>
  </RecipeDef>

  <RecipeDef ParentName="HeavyEnigmaticMechanoidRecipe">
    <defName>BOR_Enigmatic_Tunneler</defName>
    <label>gestate enigmatic tunneler</label>
    <description>Gestate a enigmatic tunneler mechanoid.</description>
    <researchPrerequisite>StandardEnigmaticMechtech</researchPrerequisite>
    <ingredients Inherit="False">
      <li>
        <filter>
          <thingDefs>
            <li>BOR_QuasarAlloy</li>
          </thingDefs>
        </filter>
        <count>150</count>
      </li>
      <li>
        <filter>
          <thingDefs>
            <li>BOR_Tenebrite</li>
          </thingDefs>
        </filter>
        <count>75</count>
      </li>
      <li>
        <filter>
          <thingDefs>
            <li>BOR_ComponentIII</li>
          </thingDefs>
        </filter>
        <count>4</count>
      </li>
      <li>
        <filter>
          <thingDefs>
            <li>SubcoreRegular</li>
          </thingDefs>
        </filter>
        <count>1</count>
      </li>
    </ingredients>
    <products>
      <BOR_Enigmatic_Mech_Tunneler>1</BOR_Enigmatic_Mech_Tunneler>
    </products>
    <descriptionHyperlinks>
      <ThingDef>BOR_Enigmatic_Mech_Tunneler</ThingDef>
    </descriptionHyperlinks>
  </RecipeDef>

</Defs>