<?xml version="1.0" encoding="UTF-8"?>
<Defs>
	<CombatExtended.AmmoSetDef>
		<defName>BOR_AmmoSet_Gen3_pistol</defName>
		<label>gen3 cartridges pistol</label>
		<ammoTypes>
			<BOR_Ammo_PistolCharged_N>BOR_Bullet_Charged_III_Pistol_N</BOR_Ammo_PistolCharged_N>
			<BOR_Ammo_PistolCharged_AP_N>BOR_Bullet_Charged_III_Pistol_AP_N</BOR_Ammo_PistolCharged_AP_N>
			<BOR_Ammo_PistolCharged_Ion_N>BOR_Bullet_Charged_III_Pistol_Ion_N</BOR_Ammo_PistolCharged_Ion_N>
			<Ammo_6mmRailgun_Sabot>Bullet_6mmRailgun_Sabot</Ammo_6mmRailgun_Sabot>
			<BOR_Ammo_6mmRailgun_TC>BOR_Bullet_6mmRailgun_TC</BOR_Ammo_6mmRailgun_TC>
		</ammoTypes>
	</CombatExtended.AmmoSetDef>

	<CombatExtended.AmmoSetDef>
		<defName>BOR_AmmoSet_Gen3_shotgun</defName>
		<label>gen3 cartridges shotgun</label>
		<ammoTypes>
			<BOR_Ammo_ShotgunCharged_N>BOR_Bullet_Charged_III_Shotgun_N</BOR_Ammo_ShotgunCharged_N>
			<BOR_Ammo_ShotgunCharged_CA_Slug>BOR_Bullet_Charged_III_Shotgun_Slug_N</BOR_Ammo_ShotgunCharged_CA_Slug>
			<BOR_Ammo_ShotgunCharged_Ion_N>BOR_Bullet_Charged_III_Shotgun_Ion_N</BOR_Ammo_ShotgunCharged_Ion_N>
			<Ammo_8mmRailgun_Sabot>Bullet_8mmRailgun_Sabot</Ammo_8mmRailgun_Sabot>
			<BOR_Ammo_8mmRailgun_TC>BOR_Bullet_8mmRailgun_TC</BOR_Ammo_8mmRailgun_TC>
		</ammoTypes>
	</CombatExtended.AmmoSetDef>

	<CombatExtended.AmmoSetDef>
		<defName>BOR_AmmoSet_Gen3_rifle</defName>
		<label>gen3 cartridges rifle</label>
		<ammoTypes>
			<BOR_Ammo_RifleCharged_N>BOR_Bullet_Charged_III_Rifle_N</BOR_Ammo_RifleCharged_N>
			<BOR_Ammo_RifleCharged_AP_N>BOR_Bullet_Charged_III_Rifle_AP_N</BOR_Ammo_RifleCharged_AP_N>
			<BOR_Ammo_RifleCharged_Ion_N>BOR_Bullet_Charged_III_Rifle_Ion_N</BOR_Ammo_RifleCharged_Ion_N>
			<Ammo_8mmRailgun_Sabot>Bullet_8mmRailgun_Sabot</Ammo_8mmRailgun_Sabot>
			<BOR_Ammo_8mmRailgun_TC>BOR_Bullet_8mmRailgun_TC</BOR_Ammo_8mmRailgun_TC>
		</ammoTypes>
	</CombatExtended.AmmoSetDef>

	<CombatExtended.AmmoSetDef>
		<defName>BOR_AmmoSet_Gen3_lmg</defName>
		<label>gen3 cartridges lmg</label>
		<ammoTypes>
			<BOR_Ammo_HeavyCharged_N>BOR_Bullet_Charged_III_Heavy_N</BOR_Ammo_HeavyCharged_N>
			<BOR_Ammo_HeavyCharged_AP_N>BOR_Bullet_Charged_III_Heavy_AP_N</BOR_Ammo_HeavyCharged_AP_N>
			<BOR_Ammo_HeavyCharged_Ion_N>BOR_Bullet_Charged_III_Heavy_Ion_N</BOR_Ammo_HeavyCharged_Ion_N>
			<BOR_Ammo_12mmRailgun_TC>Bullet_12mmRailgun_Sabot</BOR_Ammo_12mmRailgun_TC>
			<BOR_Ammo_12mmRailgun_TC>BOR_Bullet_12mmRailgun_TC</BOR_Ammo_12mmRailgun_TC>
		</ammoTypes>
	</CombatExtended.AmmoSetDef>
</Defs>