<Patch>

	

	<Operation Class="PatchOperationAdd">
		<xpath>Defs/ThingDef[defName="BOR_Quasar_Apparel_ShieldBelt"]/statBases</xpath>
		<value>
			<Bulk>2</Bulk>
			<WornBulk>0</WornBulk>
		</value>
	</Operation>

	<Operation Class="PatchOperationReplace">
		<xpath>Defs/ThingDef[defName="BOR_Quasar_Apparel_ShieldBelt"]/statBases/EnergyShieldRechargeRate</xpath>
		<value>
			<EnergyShieldRechargeRate>0.438</EnergyShieldRechargeRate>
		</value>
	</Operation>

	<Operation Class="PatchOperationReplace">
		<xpath>Defs/ThingDef[defName="BOR_Quasar_Apparel_ShieldBelt"]/statBases/EnergyShieldEnergyMax</xpath>
		<value>
			<EnergyShieldEnergyMax>3.713</EnergyShieldEnergyMax>
		</value>
	</Operation>

</Patch>